bioage_tools/__init__.py
bioage_tools/_version.py
bioage_tools/accelerations.py
bioage_tools/explainer.py
bioage_tools/utils.py
bioage_tools-0.4.0.dist-info/METADATA
bioage_tools-0.4.0.dist-info/WHEEL
bioage_tools-0.4.0.dist-info/RECORD
