Metadata-Version: 2.4
Name: bioage-tools
Version: 0.4.0
Summary: Bioage tools package
Project-URL: Homepage, https://github.com/mike-live/bioage-tools
Project-URL: Bug Tracker, https://github.com/mike-live/bioage-tools/issues
Author-email: Mikhail Krivonosov <krivonosov@itmm.unn.ru>
Classifier: Operating System :: OS Independent
Classifier: Programming Language :: Python :: 3
Requires-Python: >=3.7
Requires-Dist: matplotlib>=3.6.2
Requires-Dist: numpy>=1.15.0
Requires-Dist: pandas
Requires-Dist: regression-bias-corrector
Requires-Dist: scikit-learn
Requires-Dist: shap
